AUTHORS
CHANGELOG.rst
LICENSE
MANIFEST.in
README.rst
setup.py
dbag/__init__.py
dbag/dbag_metric_types.py
dbag/manager.py
dbag/metric_types.py
dbag/models.py
dbag/urls.py
dbag/views.py
dbag.egg-info/PKG-INFO
dbag.egg-info/SOURCES.txt
dbag.egg-info/dependency_links.txt
dbag.egg-info/requires.txt
dbag.egg-info/top_level.txt
dbag/fixtures/dbag_initial_metrics.json
dbag/management/__init__.py
dbag/management/commands/__init__.py
dbag/management/commands/dbag_collect_metrics.py
dbag/management/commands/dbag_fake_metrics.py
dbag/management/commands/dbag_init.py
dbag/management/commands/dbag_output_cronjob.py
dbag/migrations/0001_initial.py
dbag/migrations/__init__.py
dbag/static/dbag/css/dashboard.css
dbag/static/dbag/js/dashboard.js
dbag/static/dbag/js/excanvas.min.js
dbag/static/dbag/js/jquery.min.js
dbag/static/dbag/js/metric.js
dbag/static/dbag/js/flot/jquery.flot.min.js
dbag/templates/dbag/base.html
dbag/templates/dbag/detail.html
dbag/templates/dbag/index.html
tests/__init__.py
tests/models.py
tests/test_urls.py
tests/tests.py