Metadata-Version: 1.0
Name: dbag
Version: 0.1.2
Summary: 
